python_request_fanout
