Metadata-Version: 2.1
Name: python-request-fanout
Version: 1.0.1
Summary: make multiple requests concurrently and get their responses
Home-page: https://github.com/Eitol/python_request_fanout
Author: Hector Oliveros
Author-email: hector.oliveros.leon@gmail.com
License: MIT
Platform: UNKNOWN
Classifier: License :: OSI Approved :: MIT License
Classifier: Programming Language :: Python :: 3.7
